README.rst
setup.cfg
setup.py
Rigidity.egg-info/PKG-INFO
Rigidity.egg-info/SOURCES.txt
Rigidity.egg-info/dependency_links.txt
Rigidity.egg-info/top_level.txt
rigidity/__init__.py
rigidity/errors.py
rigidity/rules.py