Metadata-Version: 1.0
Name: Rigidity
Version: 1.3.0
Summary: Data-validating CSV wrapper.
Home-page: UNKNOWN
Author: Austin Hartzheim
Author-email: austin@austinhartzheim.me
License: GNU GPL v3
Platform: UNKNOWN
